{"sections":{"1649736990418e8d03":{"type":"linklist","settings":{"menu":"main-menu","alignment":"a-center","section_padding":"top"}},"banner":{"type":"template-header","settings":{"full_width":true,"image":"{{ collection.image }}","scale":2,"banner_height":400,"float_header":true,"heading":"","subheading":"","alignment":"a-center","collection_image":false,"show_countdown":true}},"16507787004f2e12a0":{"type":"linklist","settings":{"menu":"yurume-sns","alignment":"a-center","section_padding":"top"}},"main":{"type":"main-collection","blocks":{"a8162060-cb0e-4be7-91eb-83a96e11ad84":{"type":"filter","settings":{}},"a693520f-e2ed-48e0-aaae-58e0dc5dcc3f":{"type":"sort_by","settings":{}}},"block_order":["a8162060-cb0e-4be7-91eb-83a96e11ad84","a693520f-e2ed-48e0-aaae-58e0dc5dcc3f"],"settings":{"items_per_page":48,"items_per_row":2,"mobile_items_per_row":true,"show_count":true}},"16694758655705a8c0":{"type":"apps","blocks":{"5ee594fa-4e9e-4267-9c6e-f11496d14762":{"type":"shopify:\/\/apps\/rempro\/blocks\/display-recent-view-products\/bf7dbc8e-7e97-487b-8543-1123a8c287bf","settings":{"rempro_block_title":"最近閲覧したアイテム","rempro_block_alingment":"center","rempro_block_title_size":28,"rempro_block_columns":6,"rempro_block_product_image_fit":"contain","rempro_block_product_image_height":200,"rempro_block_product_title_size":18,"rempro_block_product_title_length":20,"show_tax":false,"text_tax":"(税込)","alignment_tax":"right","currency":"¥"}}},"block_order":["5ee594fa-4e9e-4267-9c6e-f11496d14762"],"settings":{"full_width":true,"section_padding":"top"}},"16497370201f877cee":{"type":"image-gallery","blocks":{"1649737020205eb5dc-2":{"type":"image","settings":{"image":"shopify:\/\/shop_images\/D8F0316C-E2B8-438E-B14A-8EBFF2A16450.jpg","image_width":"33","title":"果凜@k.t.rinrin","subheading_text":"","link_text":"チェックする","link":"https:\/\/girls-crush.jp\/collections\/karin","text_color":"#ffffff","overlay_color":"#000000"}},"1649737020205eb5dc-0":{"type":"image","disabled":true,"settings":{"image":"shopify:\/\/shop_images\/2E515E88-3BD0-4C12-8114-9FBCE7CA72CF.jpg","image_width":"33","title":"霞@tgrhijj","subheading_text":"","link_text":"チェックする","link":"https:\/\/girls-crush.jp\/collections\/kasumi","text_color":"#ffffff","overlay_color":"#000000"}},"1649737020205eb5dc-1":{"type":"image","settings":{"image":"shopify:\/\/shop_images\/S__70090819_resize.jpg","image_width":"33","title":"緩苺@yy0904._","subheading_text":"","link_text":"チェックする","link":"https:\/\/girls-crush.jp\/collections\/yurume","text_color":"#ffffff","overlay_color":"#000000"}}},"block_order":["1649737020205eb5dc-2","1649737020205eb5dc-0","1649737020205eb5dc-1"],"settings":{"full_width":true,"title":"BRAND PRODUCER","heading_size":24,"subheading_size":18,"image_padding":"no-padding","section_padding":"both"}},"165027814925b1878e":{"type":"text-with-icons","blocks":{"165027814981f80edb-0":{"type":"text_block","settings":{"icon":"heart","link":"https:\/\/www.instagram.com\/girlscrush.jp\/","title":"安心・安全！","subheading":"<p>日本の会社が運営している韓国通販サイト！<br\/>困ったことはインスタから気軽にDMしてね♪<br\/>スタッフがどこよりも丁寧にお答えします！<\/p>"}},"165027814981f80edb-1":{"type":"text_block","settings":{"icon":"star","link":"","title":"レビューでスタバチケット！","subheading":"<p>感想を教えてくれたら500円分のスタバチケットをプレゼント★みんなの声をぜひ参考にさせてください！<\/p>"}},"165027814981f80edb-2":{"type":"text_block","disabled":true,"settings":{"icon":"gift","link":"","title":"お友達紹介でポイントGET！","subheading":"<p>ガルクラを友達に紹介してくれたら500ポイントプレゼント★<\/p><p>紹介された友達にもポイントがプレゼントされるよ！<br\/>少しでも多くの人に知ってもらえたら嬉しいな！<\/p>"}},"11557e86-e86f-4feb-a5a9-eca512357d4a":{"type":"text_block","settings":{"icon":"truck","link":"","title":"6,000円以上で送料無料！","subheading":"<p>ガルクラはプチプラアイテムがたくさん！<br\/>いろんなジャンルのアイテムを組み合わせて<br\/>お得にお買い物を楽しんでね♪<\/p>"}}},"block_order":["165027814981f80edb-0","165027814981f80edb-1","165027814981f80edb-2","11557e86-e86f-4feb-a5a9-eca512357d4a"],"settings":{"title":"","text_align":"center","color_scheme":"2","section_padding":"both"}},"1649736994e412031e":{"type":"accordion","blocks":{"164973699478bcc399-0":{"type":"panel","settings":{"heading":"お支払い方法について","content":"<p>クレジットカード各種・Amazon Pay・あと払いペイディ（コンビニ払いまたは銀行振込）・QR決済（PayPay、メルペイ）Apple Pay・Google Pay・がご利用可能です。<\/p>"}},"164973699478bcc399-1":{"type":"panel","settings":{"heading":"送料について","content":"<p>6,000円以上のご注文で送料無料です。3,000〜6,000円のご注文で送料が549円。1〜2,999円のご注文で送料が998円です。<\/p>"}},"164973699478bcc399-2":{"type":"panel","settings":{"heading":"配送について","content":"<p>15営業日が目安ですが、仕入れ状況によっては遅くなる場合もあります。当ショップが定める基準日を超えて遅くなる場合は、<a href=\"https:\/\/girls-crush.jp\/policies\/refund-policy\" target=\"_blank\" title=\"https:\/\/girls-crush.jp\/policies\/refund-policy\">返金ポリシー<\/a>に記載の通りご返金をいたします。<\/p>"}},"c3952d7e-c143-4df7-a224-a7109980363f":{"type":"panel","settings":{"heading":"返品・返金について","content":"<p>ご注文後のキャンセルは原則受け付けておりません。アイテムに不備がある場合はご返金が可能ですので、<a href=\"https:\/\/girls-crush.jp\/policies\/refund-policy\" target=\"_blank\" title=\"https:\/\/girls-crush.jp\/policies\/refund-policy\">返金ポリシー<\/a>をご確認ください。<\/p>"}}},"block_order":["164973699478bcc399-0","164973699478bcc399-1","164973699478bcc399-2","c3952d7e-c143-4df7-a224-a7109980363f"],"settings":{"heading":"FAQs","allow_multiple":false,"section_padding":"both"}}},"order":["1649736990418e8d03","banner","16507787004f2e12a0","main","16694758655705a8c0","16497370201f877cee","165027814925b1878e","1649736994e412031e"]}